napari_sif_reader/__init__.py
napari_sif_reader/_reader.py
napari_sif_reader/_sample_data.py
napari_sif_reader/napari.yaml
napari_sif_reader/_tests/__init__.py
napari_sif_reader/_tests/test_reader.py
napari_sif_reader/_tests/test_sample_data.py
napari_sif_reader-0.0.2.dist-info/LICENSE
napari_sif_reader-0.0.2.dist-info/METADATA
napari_sif_reader-0.0.2.dist-info/WHEEL
napari_sif_reader-0.0.2.dist-info/entry_points.txt
napari_sif_reader-0.0.2.dist-info/top_level.txt
napari_sif_reader-0.0.2.dist-info/RECORD
