Metadata-Version: 2.1
Name: napari-sif-reader
Version: 0.0.2
Summary: This is a simple wraper to read .sif format files from Andor Technology.
Home-page: https://github.com/rjlopez2/napari-sif-reader
Author: Ruben Lopez
Author-email: rjlopez2@gmail.com
License: BSD-3-Clause
Project-URL: Bug Tracker, https://github.com/rjlopez2/napari-sif-reader/issues
Project-URL: Documentation, https://github.com/rjlopez2/napari-sif-reader#README.md
Project-URL: Source Code, https://github.com/rjlopez2/napari-sif-reader
Project-URL: User Support, https://github.com/rjlopez2/napari-sif-reader/issues
Classifier: Development Status :: 2 - Pre-Alpha
Classifier: Framework :: napari
Classifier: Intended Audience :: Developers
Classifier: License :: OSI Approved :: BSD License
Classifier: Operating System :: OS Independent
Classifier: Programming Language :: Python
Classifier: Programming Language :: Python :: 3
Classifier: Programming Language :: Python :: 3 :: Only
Classifier: Programming Language :: Python :: 3.8
Classifier: Programming Language :: Python :: 3.9
Classifier: Programming Language :: Python :: 3.10
Classifier: Topic :: Scientific/Engineering :: Image Processing
Requires-Python: >=3.8
License-File: LICENSE
Requires-Dist: numpy
Requires-Dist: sif-parser
Provides-Extra: testing
Requires-Dist: tox ; extra == 'testing'
Requires-Dist: pytest ; extra == 'testing'
Requires-Dist: pytest-cov ; extra == 'testing'
Requires-Dist: pillow ; extra == 'testing'
